License.txt
setup.cfg
setup.py
yungestgram/__init__.py
yungestgram/exceptions.py
yungestgram/handlers.py
yungestgram/yungestgram.py
yungestgram.egg-info/PKG-INFO
yungestgram.egg-info/SOURCES.txt
yungestgram.egg-info/dependency_links.txt
yungestgram.egg-info/requires.txt
yungestgram.egg-info/top_level.txt